mtasanpystatus/__init__.py
mtasanpystatus-6.dist-info/licenses/LICENSE
mtasanpystatus-6.dist-info/METADATA
mtasanpystatus-6.dist-info/WHEEL
mtasanpystatus-6.dist-info/top_level.txt
mtasanpystatus-6.dist-info/RECORD
