Metadata-Version: 2.4
Name: mtasanpystatus
Version: 6
Summary: Multi Theft Auto San Andreas Server Monitoring Library Using Python
Home-page: https://github.com/ieoub/mtasanpystatus
Author: ieoub
Author-email: rib7daily@gmail.com
Classifier: Programming Language :: Python :: 3
Classifier: License :: OSI Approved :: MIT License
Classifier: Operating System :: OS Independent
Requires-Python: >=3.6
License-File: LICENSE
Provides-Extra: dev
Requires-Dist: pytest>=6.0; extra == "dev"
Requires-Dist: twine>=3.0; extra == "dev"
Dynamic: author
Dynamic: author-email
Dynamic: classifier
Dynamic: description
Dynamic: description-content-type
Dynamic: home-page
Dynamic: license-file
Dynamic: provides-extra
Dynamic: requires-python
Dynamic: summary
